toolforge_cli/__init__.py
toolforge_cli/cli.py
toolforge_cli/config.py
toolforge_cli-0.3.4.dist-info/LICENSE
toolforge_cli-0.3.4.dist-info/METADATA
toolforge_cli-0.3.4.dist-info/WHEEL
toolforge_cli-0.3.4.dist-info/entry_points.txt
toolforge_cli-0.3.4.dist-info/RECORD
