Metadata-Version: 2.1
Name: toolforge-cli
Version: 0.3.4
Summary: Toolforge client
Home-page: https://gitlab.wikimedia.org/repos/cloud/toolforge/toolforge-cli
License: GPL-3.0-or-later
Author: David Caro
Author-email: dcaro@wikimedia.org
Requires-Python: >=3.7,<4.0
Classifier: Environment :: Console
Classifier: Intended Audience :: Developers
Classifier: Intended Audience :: System Administrators
Classifier: License :: OSI Approved :: GNU General Public License v3 or later (GPLv3+)
Classifier: Programming Language :: Python :: 3
Classifier: Programming Language :: Python :: 3.7
Classifier: Programming Language :: Python :: 3.8
Classifier: Programming Language :: Python :: 3.9
Classifier: Programming Language :: Python :: 3.10
Classifier: Programming Language :: Python :: 3.11
Requires-Dist: PyYAML (>=6.0,<7.0)
Requires-Dist: click (>=8.0.3,<9.0.0)
Requires-Dist: cryptography (>=36.0.1,<37.0.0)
Requires-Dist: requests (>=2.27.1,<3.0.0)
Requires-Dist: tabulate (>=0.9.0,<0.10.0)
Requires-Dist: toolforge-weld (>=1.1,<2.0)
Requires-Dist: urllib3 (>=1.26.8,<2.0.0)
Project-URL: Documentation, https://wikitech.wikimedia.org/wiki/Help:Toolforge
